rapidocr_api/__init__.py
rapidocr_api/main.py
rapidocr_api-0.2.0.dist-info/LICENSE
rapidocr_api-0.2.0.dist-info/METADATA
rapidocr_api-0.2.0.dist-info/WHEEL
rapidocr_api-0.2.0.dist-info/entry_points.txt
rapidocr_api-0.2.0.dist-info/top_level.txt
rapidocr_api-0.2.0.dist-info/RECORD
