Metadata-Version: 2.1
Name: rapidocr-api
Version: 0.2.0
Summary: A cross platform OCR API Library based on RapidOCR
Home-page: https://github.com/RapidAI/RapidOCRAPI
Download-URL: https://github.com/RapidAI/RapidOCRAPI.git
Author: SWHL
Author-email: liekkaskono@163.com
License: Apache-2.0
Keywords: ocr,text_detection,text_recognition,db,onnxruntime,paddleocr,openvino,rapidocr
Platform: Any
Classifier: Programming Language :: Python :: 3.6
Classifier: Programming Language :: Python :: 3.7
Classifier: Programming Language :: Python :: 3.8
Classifier: Programming Language :: Python :: 3.9
Classifier: Programming Language :: Python :: 3.10
Classifier: Programming Language :: Python :: 3.11
Classifier: Programming Language :: Python :: 3.12
Classifier: Programming Language :: Python :: 3.13
Requires-Python: >=3.6
License-File: LICENSE
Requires-Dist: requests
Requires-Dist: fastapi
Requires-Dist: uvicorn[standard]
Requires-Dist: python-multipart
Requires-Dist: rapidocr
